{"entities": [{"name": "student recruitment companies", "type": "ORGANIZATION", "salience": 0.033472221344709396}, {"name": "Chandigarh", "type": "LOCATION", "salience": 0.024941325187683105}, {"name": "employees", "type": "PERSON", "salience": 0.023574665188789368}, {"name": "HR Executive", "type": "PERSON", "salience": 0.020788833498954773}, {"name": "employee", "type": "PERSON", "salience": 0.01547907292842865}, {"name": "company", "type": "ORGANIZATION", "salience": 0.014882931485772133}, {"name": "Jaspreet Kaur Oceanic Consultants", "type": "PERSON", "salience": 0.014713890850543976}, {"name": "company", "type": "ORGANIZATION", "salience": 0.013163945637643337}, {"name": "Consultants", "type": "PERSON", "salience": 0.011815235950052738}, {"name": "offices", "type": "LOCATION", "salience": 0.011747237294912338}, {"name": "HR Executive", "type": "PERSON", "salience": 0.009881503880023956}, {"name": "Oceanic Consultants", "type": "PERSON", "salience": 0.008354798890650272}, {"name": "organization", "type": "ORGANIZATION", "salience": 0.007968212477862835}, {"name": "world", "type": "LOCATION", "salience": 0.007872715592384338}, {"name": "Oceanic Consultants Pvt. Ltd - Chandigarh", "type": "ORGANIZATION", "salience": 0.007814503274857998}, {"name": "Australia", "type": "LOCATION", "salience": 0.005461531225591898}, {"name": "joinee", "type": "PERSON", "salience": 0.004801176022738218}, {"name": "joinee", "type": "PERSON", "salience": 0.004801176022738218}, {"name": "joinee", "type": "PERSON", "salience": 0.004796039313077927}, {"name": "Faridabad", "type": "LOCATION", "salience": 0.004734421148896217}, {"name": "Melbourne", "type": "LOCATION", "salience": 0.004654356744140387}, {"name": "India", "type": "LOCATION", "salience": 0.004654356744140387}, {"name": "Punjab", "type": "LOCATION", "salience": 0.004259570501744747}, {"name": "Haryana", "type": "LOCATION", "salience": 0.004006642382591963}, {"name": "Mohali", "type": "LOCATION", "salience": 0.004005601163953543}, {"name": "candidate", "type": "PERSON", "salience": 0.00398284662514925}, {"name": "interviews", "type": "EVENT", "salience": 0.00398284662514925}, {"name": "interviews", "type": "WORK_OF_ART", "salience": 0.00398284662514925}, {"name": "exit employees", "type": "PERSON", "salience": 0.003933147061616182}, {"name": "exit employee", "type": "PERSON", "salience": 0.003926226869225502}, {"name": "Business card", "type": "CONSUMER_GOOD", "salience": 0.0037040580064058304}, {"name": "Offer Letter", "type": "WORK_OF_ART", "salience": 0.0037040580064058304}, {"name": "Promotions", "type": "WORK_OF_ART", "salience": 0.0037000938318669796}, {"name": "employees", "type": "PERSON", "salience": 0.003571573179215193}, {"name": "round", "type": "EVENT", "salience": 0.003382281633093953}, {"name": "company", "type": "ORGANIZATION", "salience": 0.0030754664912819862}, {"name": "HR Officer", "type": "PERSON", "salience": 0.0030112669337540865}, {"name": "festivals", "type": "EVENT", "salience": 0.003002157900482416}, {"name": "joiner", "type": "PERSON", "salience": 0.0029734985437244177}, {"name": "Relocation", "type": "LOCATION", "salience": 0.002964044688269496}, {"name": "Manager", "type": "PERSON", "salience": 0.0028685969300568104}, {"name": "New Joinee", "type": "PERSON", "salience": 0.002837533364072442}, {"name": "consultants", "type": "PERSON", "salience": 0.0027489191852509975}, {"name": "celebrations", "type": "EVENT", "salience": 0.002680250909179449}, {"name": "employees", "type": "PERSON", "salience": 0.002673496026545763}, {"name": "employees", "type": "PERSON", "salience": 0.0026722303591668606}, {"name": "Office Management", "type": "PERSON", "salience": 0.002610502764582634}, {"name": "Experience letter", "type": "WORK_OF_ART", "salience": 0.0025194869376719}, {"name": "emails", "type": "WORK_OF_ART", "salience": 0.0025194869376719}, {"name": "Interviews", "type": "WORK_OF_ART", "salience": 0.0024709179997444153}, {"name": "candidates", "type": "PERSON", "salience": 0.0024695664178580046}, {"name": "company", "type": "ORGANIZATION", "salience": 0.0022995572071522474}, {"name": "branch", "type": "LOCATION", "salience": 0.002275985199958086}, {"name": "Festival", "type": "EVENT", "salience": 0.002275985199958086}, {"name": "birthday", "type": "EVENT", "salience": 0.002275985199958086}, {"name": "recruitment progress report", "type": "WORK_OF_ART", "salience": 0.0020949095487594604}, {"name": "opening", "type": "EVENT", "salience": 0.002019884530454874}, {"name": "Wedding", "type": "EVENT", "salience": 0.0019989588763564825}, {"name": "candidate", "type": "PERSON", "salience": 0.0018433278892189264}, {"name": "home", "type": "LOCATION", "salience": 0.0018373472848907113}, {"name": "office premises", "type": "LOCATION", "salience": 0.0018350462196394801}, {"name": "Short", "type": "PERSON", "salience": 0.0017553683137521148}, {"name": "appointment Letters", "type": "WORK_OF_ART", "salience": 0.0017158190021291375}, {"name": "Exit", "type": "LOCATION", "salience": 0.001695015700533986}, {"name": "enterprises", "type": "ORGANIZATION", "salience": 0.0015664632664993405}, {"name": "documentations", "type": "WORK_OF_ART", "salience": 0.0015648558037355542}, {"name": "Maya Estatz", "type": "ORGANIZATION", "salience": 0.0014834118774160743}, {"name": "Real Estate", "type": "LOCATION", "salience": 0.0014834118774160743}, {"name": "Parties", "type": "ORGANIZATION", "salience": 0.0013730534119531512}, {"name": "MAYA ESTATZ - Zirakpur", "type": "LOCATION", "salience": 0.0013546458212658763}, {"name": "Zirakpur&amp", "type": "LOCATION", "salience": 0.0013528894633054733}, {"name": "Customer", "type": "PERSON", "salience": 0.0011988995829597116}, {"name": "customer", "type": "PERSON", "salience": 0.0011981293791905046}, {"name": "Panchkula", "type": "LOCATION", "salience": 0.0011881849495694041}, {"name": "Himachal", "type": "LOCATION", "salience": 0.0011881849495694041}, {"name": "Sale Activities", "type": "EVENT", "salience": 0.001093165366910398}, {"name": "Business Administration", "type": "ORGANIZATION", "salience": 0.0010922527872025967}, {"name": "CASE STUDY", "type": "WORK_OF_ART", "salience": 0.0010896573076024652}, {"name": "RAG", "type": "ORGANIZATION", "salience": 0.0010870611295104027}, {"name": "Deliveries", "type": "EVENT", "salience": 0.0009598669712431729}, {"name": "Masters", "type": "PERSON", "salience": 0.0009592710412107408}, {"name": "IT Department", "type": "ORGANIZATION", "salience": 0.0009249892900697887}, {"name": "celebrations", "type": "EVENT", "salience": 0.0008123433217406273}, {"name": "celebration", "type": "EVENT", "salience": 0.0008123433217406273}, {"name": "celebrations", "type": "EVENT", "salience": 0.0008123433217406273}, {"name": "Tours", "type": "LOCATION", "salience": 0.0008111900533549488}, {"name": "Candidates", "type": "PERSON", "salience": 0.0008097972604446113}, {"name": "Mohali Campus - Mohali", "type": "LOCATION", "salience": 0.0007597961230203509}, {"name": "HCL Infosystems", "type": "ORGANIZATION", "salience": 0.0007582693360745907}, {"name": "Executive", "type": "PERSON", "salience": 0.0007535017211921513}, {"name": "Exit Employees", "type": "PERSON", "salience": 0.0006945142522454262}, {"name": "Human Resource Administration", "type": "ORGANIZATION", "salience": 0.0006894964608363807}, {"name": "Advertisements", "type": "WORK_OF_ART", "salience": 0.0006834603846073151}, {"name": "Central Board of Secondary education", "type": "ORGANIZATION", "salience": 0.0006445306353271008}, {"name": "Vendors", "type": "ORGANIZATION", "salience": 0.0006042622844688594}, {"name": "LTD - Chandigarh", "type": "ORGANIZATION", "salience": 0.0005965863238088787}, {"name": "Commerce", "type": "LOCATION", "salience": 0.0005663704941980541}, {"name": "Dev Samaj College for Women - Chandigarh", "type": "ORGANIZATION", "salience": 0.0005662623443640769}, {"name": "excel", "type": "CONSUMER_GOOD", "salience": 0.0005656469147652388}, {"name": "Microsoft", "type": "ORGANIZATION", "salience": 0.0005656469147652388}, {"name": "Vista", "type": "CONSUMER_GOOD", "salience": 0.0005656469147652388}, {"name": "OS", "type": "ORGANIZATION", "salience": 0.0005656469147652388}, {"name": "ERP", "type": "CONSUMER_GOOD", "salience": 0.0005653586704283953}, {"name": "HR", "type": "ORGANIZATION", "salience": 0.0005324991070665419}, {"name": "INFOSYS", "type": "ORGANIZATION", "salience": 0.00047810637624934316}, {"name": "SOLITAIRE", "type": "ORGANIZATION", "salience": 0.00040595800965093076}, {"name": "Diwali", "type": "EVENT", "salience": 0.00035786096123047173}, {"name": "Lohri", "type": "PERSON", "salience": 0.00035786096123047173}, {"name": "Christmas", "type": "EVENT", "salience": 0.00035786096123047173}, {"name": "SOLITAIRE INFOSYS PVT", "type": "ORGANIZATION", "salience": 0.00035642157308757305}, {"name": "June 2013", "type": "DATE", "salience": 0.0}, {"name": "January 2014", "type": "DATE", "salience": 0.0}, {"name": "1996", "type": "DATE", "salience": 0.0}, {"name": "January 2012", "type": "DATE", "salience": 0.0}, {"name": "May 2013", "type": "DATE", "salience": 0.0}, {"name": "January 2011", "type": "DATE", "salience": 0.0}, {"name": "October 2011", "type": "DATE", "salience": 0.0}, {"name": "2011", "type": "DATE", "salience": 0.0}, {"name": "2009", "type": "DATE", "salience": 0.0}, {"name": "2003", "type": "DATE", "salience": 0.0}, {"name": "2005", "type": "DATE", "salience": 0.0}, {"name": "six", "type": "NUMBER", "salience": 0.0}, {"name": "1", "type": "NUMBER", "salience": 0.0}, {"name": "2011", "type": "NUMBER", "salience": 0.0}, {"name": "2011", "type": "NUMBER", "salience": 0.0}, {"name": "2013", "type": "NUMBER", "salience": 0.0}, {"name": "2011", "type": "NUMBER", "salience": 0.0}, {"name": "2005", "type": "NUMBER", "salience": 0.0}, {"name": "2012", "type": "NUMBER", "salience": 0.0}, {"name": "2009", "type": "NUMBER", "salience": 0.0}, {"name": "2014", "type": "NUMBER", "salience": 0.0}, {"name": "2003", "type": "NUMBER", "salience": 0.0}, {"name": "one", "type": "NUMBER", "salience": 0.0}, {"name": "2013", "type": "NUMBER", "salience": 0.0}, {"name": "1996", "type": "NUMBER", "salience": 0.0}, {"name": "one", "type": "NUMBER", "salience": 0.0}, {"name": "one", "type": "NUMBER", "salience": 0.0}, {"name": "1", "type": "NUMBER", "salience": 0.0}, {"name": "2", "type": "NUMBER", "salience": 0.0}]}