{"entities": [{"name": "Karnataka", "type": "LOCATION", "salience": 0.026015132665634155}, {"name": "Cisco 7600", "type": "ORGANIZATION", "salience": 0.02256564050912857}, {"name": "customers", "type": "PERSON", "salience": 0.016445063054561615}, {"name": "Madhuri Sripathi Banglore", "type": "LOCATION", "salience": 0.013946201652288437}, {"name": "indeed.com/r/Madhuri- Sripathi", "type": "PERSON", "salience": 0.013946201652288437}, {"name": "customer", "type": "PERSON", "salience": 0.013393998146057129}, {"name": "teams", "type": "ORGANIZATION", "salience": 0.012275459244847298}, {"name": "Python", "type": "ORGANIZATION", "salience": 0.006528364960104227}, {"name": "customer", "type": "PERSON", "salience": 0.006185492966324091}, {"name": "regression testing", "type": "EVENT", "salience": 0.0052838632836937904}, {"name": "stress testing", "type": "EVENT", "salience": 0.0052838632836937904}, {"name": "system testing", "type": "EVENT", "salience": 0.0052838632836937904}, {"name": "performance testing", "type": "EVENT", "salience": 0.0052838632836937904}, {"name": "Testing", "type": "EVENT", "salience": 0.004832414910197258}, {"name": "CISCO IOS", "type": "CONSUMER_GOOD", "salience": 0.004714607261121273}, {"name": "router", "type": "CONSUMER_GOOD", "salience": 0.004530949052423239}, {"name": "RSTP", "type": "ORGANIZATION", "salience": 0.004026478622108698}, {"name": "clients", "type": "PERSON", "salience": 0.003696436993777752}, {"name": "team member", "type": "PERSON", "salience": 0.003683373099192977}, {"name": "System Testing", "type": "EVENT", "salience": 0.003631005296483636}, {"name": "Testing", "type": "EVENT", "salience": 0.0036300010979175568}, {"name": "project engineer", "type": "PERSON", "salience": 0.0033488550689071417}, {"name": "Senior project engineer", "type": "PERSON", "salience": 0.0033189801033586264}, {"name": "Wipro Technologies", "type": "ORGANIZATION", "salience": 0.0030886344611644745}, {"name": "project engineer", "type": "PERSON", "salience": 0.003061544382944703}, {"name": "software engineer", "type": "PERSON", "salience": 0.0030602223705500364}, {"name": "customer", "type": "PERSON", "salience": 0.0028605342376977205}, {"name": "Traffic Generators", "type": "PERSON", "salience": 0.0028492023702710867}, {"name": "release", "type": "EVENT", "salience": 0.0024899812415242195}, {"name": "pagent", "type": "PERSON", "salience": 0.0021339766681194305}, {"name": "Developer", "type": "ORGANIZATION", "salience": 0.0019483695505186915}, {"name": "Traffic generators", "type": "PERSON", "salience": 0.0019462370546534657}, {"name": "Cisco 7600 Routers", "type": "CONSUMER_GOOD", "salience": 0.001912501989863813}, {"name": "PAGENT", "type": "ORGANIZATION", "salience": 0.0018459393177181482}, {"name": "IXIA", "type": "ORGANIZATION", "salience": 0.0018197768367826939}, {"name": "Bangalore", "type": "LOCATION", "salience": 0.0016743955202400684}, {"name": "SPIRENT", "type": "ORGANIZATION", "salience": 0.0016640981193631887}, {"name": "Operating Systems", "type": "CONSUMER_GOOD", "salience": 0.0015999703900888562}, {"name": "UAE - Dubai - abu-dabhi", "type": "LOCATION", "salience": 0.0014775999588891864}, {"name": "Cisco - Bengaluru", "type": "LOCATION", "salience": 0.0014749349793419242}, {"name": "L2", "type": "ORGANIZATION", "salience": 0.0013553007738664746}, {"name": "customers", "type": "PERSON", "salience": 0.0012557579902932048}, {"name": "GIG", "type": "EVENT", "salience": 0.001009884406812489}, {"name": "team", "type": "ORGANIZATION", "salience": 0.0009376208181492984}, {"name": "UNIX", "type": "CONSUMER_GOOD", "salience": 0.0009070303640328348}, {"name": "LINUX", "type": "CONSUMER_GOOD", "salience": 0.0009070303640328348}, {"name": "images", "type": "WORK_OF_ART", "salience": 0.0008553907973691821}, {"name": "images", "type": "WORK_OF_ART", "salience": 0.0008553907973691821}, {"name": "test reports", "type": "WORK_OF_ART", "salience": 0.0007512405281886458}, {"name": "training sessions", "type": "EVENT", "salience": 0.0007509937859140337}, {"name": "Rajah", "type": "ORGANIZATION", "salience": 0.0007055390160530806}, {"name": "ARP", "type": "ORGANIZATION", "salience": 0.000704907055478543}, {"name": "ICMP", "type": "ORGANIZATION", "salience": 0.000704907055478543}, {"name": "German", "type": "LOCATION", "salience": 0.00044350893585942686}, {"name": "AT&T", "type": "ORGANIZATION", "salience": 0.00044350893585942686}, {"name": "Bharati", "type": "PERSON", "salience": 0.00044350893585942686}, {"name": "Vodafone", "type": "ORGANIZATION", "salience": 0.00044350893585942686}, {"name": "Sev1", "type": "LOCATION", "salience": 0.0004433706635609269}, {"name": "Sev2", "type": "LOCATION", "salience": 0.0004433706635609269}, {"name": "Jan2014", "type": "DATE", "salience": 0.0}, {"name": "March 2014", "type": "DATE", "salience": 0.0}, {"name": "March 2014", "type": "DATE", "salience": 0.0}, {"name": "February 2014", "type": "DATE", "salience": 0.0}, {"name": "2014", "type": "NUMBER", "salience": 0.0}, {"name": "4", "type": "NUMBER", "salience": 0.0}, {"name": "4", "type": "NUMBER", "salience": 0.0}, {"name": "04", "type": "NUMBER", "salience": 0.0}, {"name": "2014", "type": "NUMBER", "salience": 0.0}, {"name": "4", "type": "NUMBER", "salience": 0.0}, {"name": "4", "type": "NUMBER", "salience": 0.0}, {"name": "4", "type": "NUMBER", "salience": 0.0}, {"name": "-7600", "type": "NUMBER", "salience": 0.0}, {"name": "3", "type": "NUMBER", "salience": 0.0}, {"name": "4", "type": "NUMBER", "salience": 0.0}, {"name": "4", "type": "NUMBER", "salience": 0.0}, {"name": "4", "type": "NUMBER", "salience": 0.0}, {"name": "4", "type": "NUMBER", "salience": 0.0}, {"name": "4", "type": "NUMBER", "salience": 0.0}, {"name": "04", "type": "NUMBER", "salience": 0.0}, {"name": "2014", "type": "NUMBER", "salience": 0.0}, {"name": "2", "type": "NUMBER", "salience": 0.0}, {"name": "7600", "type": "NUMBER", "salience": 0.0}, {"name": "4", "type": "NUMBER", "salience": 0.0}, {"name": "04", "type": "NUMBER", "salience": 0.0}, {"name": "7600", "type": "NUMBER", "salience": 0.0}, {"name": "2", "type": "NUMBER", "salience": 0.0}, {"name": "7600", "type": "NUMBER", "salience": 0.0}]}