{"entities": [{"text": "Rishabh soni", "category": "PERSON", "start": 0, "end": 12}, {"text": "Anuppur", "category": "GPE", "start": 13, "end": 20}, {"text": "Madhya", "category": "GPE", "start": 22, "end": 28}, {"text": "Microsoft", "category": "ORG", "start": 134, "end": 143}, {"text": "January 2018", "category": "DATE", "start": 147, "end": 159}, {"text": "CSE", "category": "ORG", "start": 217, "end": 220}, {"text": "IIT Delhi", "category": "GPE", "start": 223, "end": 232}, {"text": "Specilization", "category": "PRODUCT", "start": 242, "end": 255}]}