{"entities": [{"text": "Bangalore Bengaluru", "category": "PERSON"}, {"text": "Karnataka", "category": "LOCATION"}, {"text": "Informatica Power", "category": "ORGANIZATION"}, {"text": "Karnataka", "category": "LOCATION"}, {"text": "Informatica", "category": "ORGANIZATION"}, {"text": "Infosys Limited", "category": "ORGANIZATION"}, {"text": "Chennai Training", "category": "LOCATION"}, {"text": "Infosys Limited Mysore", "category": "ORGANIZATION"}, {"text": "Karnataka", "category": "LOCATION"}, {"text": "Infosys Limited", "category": "ORGANIZATION"}, {"text": "Chennai", "category": "LOCATION"}, {"text": "Bhubaneshwar Orissa", "category": "LOCATION"}, {"text": "Junior College", "category": "ORGANIZATION"}, {"text": "Balasore Orissa", "category": "LOCATION"}, {"text": "Informatica", "category": "ORGANIZATION"}, {"text": "Tools Informatica Power Center Oracle", "category": "ORGANIZATION"}, {"text": "Hadoop", "category": "PERSON"}, {"text": "Jira Scheduling Tools Tidal", "category": "ORGANIZATION"}, {"text": "Control-M Cloud Technology Microsoft", "category": "ORGANIZATION"}, {"text": "Healthcare", "category": "ORGANIZATION"}, {"text": "Healthcare", "category": "ORGANIZATION"}]}