{"entities": [{"text": "K. Siddharth", "category": "PERSON"}, {"text": "Microsoft", "category": "ORGANIZATION"}, {"text": "Tamil Nadu", "category": "LOCATION"}, {"text": "Microsoft Nehru Memorial College Puthanampatti", "category": "ORGANIZATION"}, {"text": "Microsoft", "category": "ORGANIZATION"}, {"text": "Nehru Memorial", "category": "LOCATION"}, {"text": "Xerox Machine", "category": "ORGANIZATION"}, {"text": "Madurai Tamil Nadu", "category": "LOCATION"}, {"text": "Tamil Nadu", "category": "LOCATION"}, {"text": "DCE Adi Sankara Polytechnic College", "category": "ORGANIZATION"}, {"text": "Tamil Nadu", "category": "LOCATION"}]}