{"entities": [{"text": "Jyotirbindu Patnaik", "category": "PERSON"}, {"text": "SAP", "category": "ORGANIZATION"}, {"text": "Bangalore Karnataka Bengaluru", "category": "PERSON"}, {"text": "Karnataka", "category": "LOCATION"}, {"text": "Bangalore Karnataka", "category": "LOCATION"}, {"text": "Sap", "category": "ORGANIZATION"}, {"text": "RCA", "category": "ORGANIZATION"}, {"text": "Sap", "category": "ORGANIZATION"}, {"text": "SAP", "category": "ORGANIZATION"}, {"text": "Bristlecone India LTD", "category": "ORGANIZATION"}, {"text": "MTTR", "category": "ORGANIZATION"}, {"text": "Pingdom", "category": "LOCATION"}, {"text": "CSS", "category": "ORGANIZATION"}, {"text": "KPI", "category": "ORGANIZATION"}, {"text": "KPI", "category": "ORGANIZATION"}, {"text": "SAP", "category": "ORGANIZATION"}, {"text": "Electronics and Communication Biju Patnaik University Rayagada", "category": "ORGANIZATION"}, {"text": "Orissa", "category": "LOCATION"}]}