{"entities": [{"text": "Mumbai Maharashtra", "category": "LOCATION"}, {"text": "UK", "category": "LOCATION"}, {"text": "Custom Application Testing Services", "category": "ORGANIZATION"}, {"text": "Siebel", "category": "ORGANIZATION"}, {"text": "PMO", "category": "ORGANIZATION"}, {"text": "FMW", "category": "ORGANIZATION"}, {"text": "REIM", "category": "ORGANIZATION"}, {"text": "AP", "category": "ORGANIZATION"}, {"text": "OM", "category": "ORGANIZATION"}, {"text": "OAM OIM", "category": "ORGANIZATION"}, {"text": "SSO", "category": "ORGANIZATION"}, {"text": "RFT", "category": "ORGANIZATION"}, {"text": "RCC", "category": "ORGANIZATION"}, {"text": "Junit", "category": "PERSON"}, {"text": "JIRA", "category": "ORGANIZATION"}, {"text": "SOAPUI", "category": "LOCATION"}, {"text": "Jbehave", "category": "PERSON"}, {"text": "CMMI", "category": "ORGANIZATION"}, {"text": "ISO", "category": "ORGANIZATION"}, {"text": "Logistics SCM", "category": "ORGANIZATION"}, {"text": "Public Sector Financial Banking", "category": "ORGANIZATION"}, {"text": "Health Sciences Telecom Real Estate", "category": "ORGANIZATION"}, {"text": "Project Management Knowledge Management Performance Management", "category": "ORGANIZATION"}, {"text": "UK", "category": "LOCATION"}, {"text": "Saudi Arabia", "category": "LOCATION"}, {"text": "UBS", "category": "ORGANIZATION"}, {"text": "London UK", "category": "LOCATION"}, {"text": "UK", "category": "LOCATION"}, {"text": "TNT", "category": "ORGANIZATION"}, {"text": "Hinckley", "category": "PERSON"}, {"text": "UK", "category": "LOCATION"}, {"text": "RCUK Research Councils Swindon", "category": "ORGANIZATION"}, {"text": "UK", "category": "LOCATION"}, {"text": "Netherlands", "category": "LOCATION"}, {"text": "Citibank", "category": "ORGANIZATION"}, {"text": "USA", "category": "LOCATION"}, {"text": "Transurban", "category": "ORGANIZATION"}, {"text": "Australia", "category": "LOCATION"}, {"text": "Blue Cross Blue Shield", "category": "ORGANIZATION"}, {"text": "USA", "category": "LOCATION"}, {"text": "Mumbai Maharashtra", "category": "LOCATION"}, {"text": "Tracelink Products Tracelink", "category": "ORGANIZATION"}, {"text": "Amazon Cloud Services", "category": "ORGANIZATION"}, {"text": "Elasticache", "category": "LOCATION"}, {"text": "Dynamo", "category": "ORGANIZATION"}, {"text": "Amazon", "category": "ORGANIZATION"}, {"text": "Java Scala", "category": "LOCATION"}, {"text": "Jmeter", "category": "PERSON"}, {"text": "Karnataka", "category": "LOCATION"}, {"text": "London", "category": "LOCATION"}, {"text": "London", "category": "LOCATION"}, {"text": "Oracle", "category": "ORGANIZATION"}, {"text": "UBS", "category": "ORGANIZATION"}, {"text": "Oracle Fusion Human Capital Management", "category": "ORGANIZATION"}, {"text": "UBS", "category": "ORGANIZATION"}, {"text": "UBS", "category": "ORGANIZATION"}, {"text": "UBS", "category": "ORGANIZATION"}, {"text": "PeopleSoft", "category": "ORGANIZATION"}, {"text": "UBS", "category": "ORGANIZATION"}, {"text": "UBS", "category": "ORGANIZATION"}, {"text": "Viz.", "category": "LOCATION"}, {"text": "Workforce Management", "category": "ORGANIZATION"}, {"text": "Viz.", "category": "LOCATION"}, {"text": "UAT", "category": "ORGANIZATION"}, {"text": "Viz.", "category": "LOCATION"}, {"text": "WorkForce Management", "category": "ORGANIZATION"}, {"text": "Workforce Management", "category": "ORGANIZATION"}, {"text": "Microsoft", "category": "ORGANIZATION"}, {"text": "India USA", "category": "LOCATION"}, {"text": "Bangalore Karnataka", "category": "LOCATION"}, {"text": "UBS", "category": "ORGANIZATION"}, {"text": "Nagarjuna University BSC", "category": "ORGANIZATION"}, {"text": "Kakatiya University", "category": "ORGANIZATION"}, {"text": "Initiation Business Case Charter", "category": "ORGANIZATION"}, {"text": "Budgeting Execution Release Management", "category": "ORGANIZATION"}, {"text": "POC POS", "category": "ORGANIZATION"}, {"text": "Satisfaction Expectation Management", "category": "ORGANIZATION"}, {"text": "Project Office Project Procurement Financial Management", "category": "ORGANIZATION"}, {"text": "Organizational Governance tools Systems", "category": "ORGANIZATION"}, {"text": "Communication Organization Development", "category": "ORGANIZATION"}, {"text": "Quality Control Configuration Management", "category": "ORGANIZATION"}]}