{"entities": [{"text": "Haryana", "category": "Location", "confidence_score": 0.35}, {"text": "indeed.com/r/Urshila-Lohani/ab8d3dc6dd8b13f0", "category": "URL", "confidence_score": 0.8}, {"text": "Gurgaon", "category": "Location", "confidence_score": 0.59}, {"text": "Haryana", "category": "Location", "confidence_score": 0.45}, {"text": "May 2016", "category": "DateTime", "confidence_score": 0.8}, {"text": "2-year", "category": "DateTime", "confidence_score": 0.8}, {"text": "sales strategy", "category": "Skill", "confidence_score": 0.8}, {"text": "South India Region", "category": "Location", "confidence_score": 0.71}, {"text": "sales", "category": "Skill", "confidence_score": 0.8}, {"text": "35", "category": "Quantity", "confidence_score": 0.8}, {"text": "20", "category": "Quantity", "confidence_score": 0.8}, {"text": "50%", "category": "Quantity", "confidence_score": 0.8}, {"text": "Business development", "category": "Skill", "confidence_score": 0.8}, {"text": "5", "category": "Quantity", "confidence_score": 0.8}, {"text": "pipeline", "category": "Skill", "confidence_score": 0.8}, {"text": "32", "category": "Quantity", "confidence_score": 0.8}, {"text": "leaders", "category": "PersonType", "confidence_score": 0.4}, {"text": "Intuit", "category": "Organization", "confidence_score": 0.86}, {"text": "IBM", "category": "Organization", "confidence_score": 0.89}, {"text": "Wipro", "category": "Organization", "confidence_score": 0.86}, {"text": "McAfee", "category": "Organization", "confidence_score": 0.77}, {"text": "Airtel", "category": "Organization", "confidence_score": 0.82}, {"text": "Religare", "category": "Organization", "confidence_score": 0.79}, {"text": "Adobe", "category": "Organization", "confidence_score": 0.75}, {"text": "100%", "category": "Quantity", "confidence_score": 0.8}, {"text": "marketing", "category": "Skill", "confidence_score": 0.8}, {"text": "attendees", "category": "PersonType", "confidence_score": 0.61}, {"text": "200", "category": "Quantity", "confidence_score": 0.8}, {"text": "IT", "category": "Skill", "confidence_score": 0.8}, {"text": "$1M", "category": "Quantity", "confidence_score": 0.8}, {"text": "5%", "category": "Quantity", "confidence_score": 0.8}, {"text": "sales", "category": "Skill", "confidence_score": 0.8}, {"text": "322", "category": "Quantity", "confidence_score": 0.8}, {"text": "quarterly", "category": "DateTime", "confidence_score": 0.8}, {"text": "FY17", "category": "DateTime", "confidence_score": 0.8}, {"text": "FY18", "category": "DateTime", "confidence_score": 0.8}, {"text": "Bengaluru", "category": "Location", "confidence_score": 0.42}, {"text": "Karnataka", "category": "Location", "confidence_score": 0.62}, {"text": "June 2014 to May 2016", "category": "DateTime", "confidence_score": 0.8}, {"text": "sales", "category": "Skill", "confidence_score": 0.8}, {"text": "South India Region", "category": "Location", "confidence_score": 0.69}, {"text": "Customer Success", "category": "Skill", "confidence_score": 0.8}, {"text": "20%", "category": "Quantity", "confidence_score": 0.8}, {"text": "12%", "category": "Quantity", "confidence_score": 0.8}, {"text": "sales", "category": "Skill", "confidence_score": 0.8}, {"text": "$4M", "category": "Quantity", "confidence_score": 0.8}, {"text": "4M in", "category": "Quantity", "confidence_score": 0.8}, {"text": "sales", "category": "Skill", "confidence_score": 0.8}, {"text": "four quarters", "category": "Quantity", "confidence_score": 0.8}, {"text": "2", "category": "Quantity", "confidence_score": 0.8}, {"text": "- 100%", "category": "Quantity", "confidence_score": 0.8}, {"text": "26%", "category": "Quantity", "confidence_score": 0.8}, {"text": "IT", "category": "Skill", "confidence_score": 0.8}, {"text": "7", "category": "Quantity", "confidence_score": 0.8}, {"text": "$400K", "category": "Quantity", "confidence_score": 0.8}, {"text": "Noida", "category": "Location", "confidence_score": 0.33}, {"text": "Uttar Pradesh", "category": "Location", "confidence_score": 0.54}, {"text": "May 2013 to May 2014", "category": "DateTime", "confidence_score": 0.8}, {"text": "https://www.indeed.com/r/Urshila-Lohani/ab8d3dc6dd8b13f0?isid=rex-download&ikw=download-top&co=IN", "category": "URL", "confidence_score": 0.8}, {"text": "Business Development", "category": "Skill", "confidence_score": 0.8}, {"text": "September 2011 to April 2013", "category": "DateTime", "confidence_score": 0.8}, {"text": "Marketing", "category": "Skill", "confidence_score": 0.8}, {"text": "Pipeline Generation kits", "category": "Skill", "confidence_score": 0.8}, {"text": "Sales", "category": "Skill", "confidence_score": 0.8}, {"text": "12", "category": "Quantity", "confidence_score": 0.8}, {"text": "Q1", "category": "DateTime", "confidence_score": 0.8}, {"text": "Q2", "category": "DateTime", "confidence_score": 0.8}, {"text": "FY13", "category": "DateTime", "confidence_score": 0.8}, {"text": "quarterly", "category": "DateTime", "confidence_score": 0.8}, {"text": "100%", "category": "Quantity", "confidence_score": 0.8}, {"text": "Annual", "category": "DateTime", "confidence_score": 0.8}, {"text": "FY12", "category": "DateTime", "confidence_score": 0.8}, {"text": "FY13", "category": "DateTime", "confidence_score": 0.8}, {"text": "email", "category": "Skill", "confidence_score": 0.8}, {"text": "marketing", "category": "Skill", "confidence_score": 0.8}, {"text": "15%", "category": "Quantity", "confidence_score": 0.8}, {"text": "mentorship", "category": "Skill", "confidence_score": 0.8}, {"text": "Training", "category": "Skill", "confidence_score": 0.8}, {"text": "by 2 Months", "category": "DateTime", "confidence_score": 0.8}, {"text": "50%", "category": "Quantity", "confidence_score": 0.8}, {"text": "EDUCATION", "category": "Skill", "confidence_score": 0.8}, {"text": "Tech", "category": "Skill", "confidence_score": 0.8}, {"text": "Engineering", "category": "Skill", "confidence_score": 0.8}, {"text": "August 2007 to May 2011", "category": "DateTime", "confidence_score": 0.8}]}